borgini/__init__.py
borgini/__main__.py
borgini/_core.py
borgini/_main.py
borgini/_version.py
borgini/config.py
borgini/funcs.py
borgini/parser.py
borgini/py.typed
borgini-1.2.0.dist-info/entry_points.txt
borgini-1.2.0.dist-info/LICENSE
borgini-1.2.0.dist-info/WHEEL
borgini-1.2.0.dist-info/METADATA
borgini-1.2.0.dist-info/RECORD
