Metadata-Version: 2.1
Name: borgini
Version: 1.2.0
Summary: ini config for borg backup
Home-page: https://pypi.org/project/borgini/
License: MIT
Keywords: backup,borg,config,deduplicate,ini
Author: jshwi
Author-email: stephen@jshwisolutions.com
Maintainer: jshwi
Maintainer-email: stephen@jshwisolutions.com
Requires-Python: >=3.8,<4.0
Classifier: License :: OSI Approved :: MIT License
Classifier: Programming Language :: Python :: 3
Classifier: Programming Language :: Python :: 3.8
Classifier: Programming Language :: Python :: 3.9
Classifier: Programming Language :: Python :: 3.10
Requires-Dist: borgbackup (>=1.1.15,<2.0.0)
Requires-Dist: pygments (>=2.6.1,<3.0.0)
Project-URL: Documentation, https://borgini.readthedocs.io/en/latest
Project-URL: Repository, https://github.com/jshwi/borgini
